files/__init__.py
files/data.py
CSULB_Upload_Dataset-0.1.0.dist-info/METADATA
CSULB_Upload_Dataset-0.1.0.dist-info/WHEEL
CSULB_Upload_Dataset-0.1.0.dist-info/top_level.txt
CSULB_Upload_Dataset-0.1.0.dist-info/RECORD
